goldenowl/__init__.py
goldenowl/asset/__init__.py
goldenowl/asset/asset.py
goldenowl/portfolio/__init__.py
goldenowl/portfolio/holding.py
goldenowl/portfolio/portfolio.py
goldenowl/portfolio/simplePut.py
goldenowl-4.2.3.dist-info/LICENSE
goldenowl-4.2.3.dist-info/METADATA
goldenowl-4.2.3.dist-info/WHEEL
goldenowl-4.2.3.dist-info/top_level.txt
goldenowl-4.2.3.dist-info/RECORD
