Metadata-Version: 2.1
Name: goldenowl
Version: 4.2.3
Summary: Tools for financial analysis
Home-page: https://github.com/nishanth-/goldenowl
Author: Nishanth (nishanth-)
Author-email: 
License: MIT
Download-URL: https://github.com/nishanth-/goldenowl/archive/refs/tags/v_423.tar.gz
Keywords: finance,investment,quant
Platform: UNKNOWN
Classifier: Development Status :: 3 - Alpha
Classifier: Intended Audience :: Developers
Classifier: Topic :: Software Development :: Build Tools
Classifier: License :: OSI Approved :: MIT License
Classifier: Programming Language :: Python :: 3
Classifier: Programming Language :: Python :: 3.4
Classifier: Programming Language :: Python :: 3.5
Classifier: Programming Language :: Python :: 3.6
Requires-Dist: pandas (>=1.1.5)
Requires-Dist: xirr (>=0.1.6)
Requires-Dist: numpy (>=1.19.5)
